MANIFEST.in
README.md
setup.py
graspy/__init__.py
graspy.egg-info/PKG-INFO
graspy.egg-info/SOURCES.txt
graspy.egg-info/dependency_links.txt
graspy.egg-info/requires.txt
graspy.egg-info/top_level.txt
graspy/cluster/__init__.py
graspy/cluster/autogmm.py
graspy/cluster/base.py
graspy/cluster/gclust.py
graspy/cluster/kclust.py
graspy/datasets/__init__.py
graspy/datasets/base.py
graspy/datasets/drosophila/left_adjacency.csv
graspy/datasets/drosophila/left_cell_labels.csv
graspy/datasets/drosophila/right_adjacency.csv
graspy/datasets/drosophila/right_cell_labels.csv
graspy/embed/__init__.py
graspy/embed/ase.py
graspy/embed/base.py
graspy/embed/lse.py
graspy/embed/mase.py
graspy/embed/mds.py
graspy/embed/omni.py
graspy/embed/svd.py
graspy/inference/__init__.py
graspy/inference/base.py
graspy/inference/latent_distribution_test.py
graspy/inference/latent_position_test.py
graspy/match/__init__.py
graspy/match/gmp.py
graspy/match/skp.py
graspy/models/__init__.py
graspy/models/base.py
graspy/models/er.py
graspy/models/rdpg.py
graspy/models/sbm.py
graspy/pipeline/__init__.py
graspy/pipeline/mug2vec.py
graspy/plot/__init__.py
graspy/plot/plot.py
graspy/simulations/__init__.py
graspy/simulations/rdpg_corr.py
graspy/simulations/simulations.py
graspy/simulations/simulations_corr.py
graspy/subgraph/__init__.py
graspy/subgraph/sg.py
graspy/utils/__init__.py
graspy/utils/ptr.py
graspy/utils/utils.py