Metadata-Version: 2.1
Name: graspy
Version: 0.3.0
Summary: A set of python modules for graph statistics
Home-page: https://github.com/neurodata/graspy
Author: ('Eric Bridgeford, Jaewon Chung, Benjamin Pedigo, Bijan Varjavand',)
Author-email: j1c@jhu.edu
License: Apache License 2.0
Platform: UNKNOWN
Classifier: Development Status :: 3 - Alpha
Classifier: Intended Audience :: Science/Research
Classifier: Topic :: Scientific/Engineering :: Mathematics
Classifier: License :: OSI Approved :: Apache Software License
Classifier: Programming Language :: Python :: 3
Classifier: Programming Language :: Python :: 3.6
Classifier: Programming Language :: Python :: 3.7
